repogif/__init__.py
repogif/generator.py
repogif/templates/__init__.py
repogif/templates/template1/__init__.py
repogif/templates/template1/pointer.png
repogif/templates/template1/template.html
repogif/templates/template2/__init__.py
repogif/templates/template2/pointer.png
repogif/templates/template2/template.html
repogif/templates/template3/__init__.py
repogif/templates/template3/template.html
repogif/templates/template4/__init__.py
repogif/templates/template4/template.html
repogif/templates/template5/__init__.py
repogif/templates/template5/template.html
repogif/templates/template6/__init__.py
repogif/templates/template6/template.html
repogif/templates/template7/__init__.py
repogif/templates/template7/template.html
repogif/templates/template8/__init__.py
repogif/templates/template8/template.html
repogif/templates/template9/__init__.py
repogif/templates/template9/template.html
repogif-0.0.4.dist-info/METADATA
repogif-0.0.4.dist-info/WHEEL
repogif-0.0.4.dist-info/entry_points.txt
repogif-0.0.4.dist-info/top_level.txt
repogif-0.0.4.dist-info/RECORD
