Metadata-Version: 2.4
Name: repogif
Version: 0.0.4
Summary: Generate beautiful animated GIFs that mimic GitHub repo stars/forks with realistic visuals. Perfect for social sharing, repo previews, documentation, or just for fun.
Home-page: https://github.com/jhd3197/repogif
Author: Juan Denis
Author-email: juan@vene.co
Classifier: Programming Language :: Python :: 3
Classifier: License :: OSI Approved :: MIT License
Classifier: Operating System :: OS Independent
Requires-Dist: Pillow
Requires-Dist: imageio
Requires-Dist: imageio-ffmpeg
Requires-Dist: numpy
Requires-Dist: playwright
Dynamic: author
Dynamic: author-email
Dynamic: classifier
Dynamic: description
Dynamic: description-content-type
Dynamic: home-page
Dynamic: requires-dist
Dynamic: summary
